<?xml version="1.0" encoding="utf-8"?>
<!DOCTYPE hibernate-mapping PUBLIC "-//Hibernate/Hibernate Mapping DTD 3.0//EN"
"http://hibernate.sourceforge.net/hibernate-mapping-3.0.dtd">
<!-- 
    Mapping file autogenerated by MyEclipse Persistence Tools
-->
<hibernate-mapping>
    <class name="edu.model.Student" table="STUDENT" schema="STUDENTDEV">
        <id name="studentNo" type="long" column="SNO">
            <generator class="sequence" >
            <param name="sequence">STUDENTNO_SEQ</param>
            </generator>
        </id>
        <!--<many-to-one name="unCourse" class="edu.model.UnCourse" fetch="select">
            <column name="CNO" scale="0" />
        </many-to-one>
        --><property name="studentName" type="java.lang.String">
            <column name="SNAME" length="40" />
        </property>
    </class>
</hibernate-mapping>
